{
    "id": "the-husl",
    "symbol": "husl",
    "name": "The HUSL",
    "platforms": {
        "ethereum": "0xa2881f7f441267042f9778ffa0d4f834693426be"
    },
    "hashing_algorithm": null,
    "categories": [
        "Music",
        "Non-Fungible Tokens (NFT)"
    ],
    "description": {
        "en": "The HUSL allows musicians to radically change the way they connect with their fans worldwide using NFTS and blockchain technology. \r\n\r\nThe HUSL gives the power back to creators, allowing them to interact on their own terms and on their own accord.\""
    },
    "country_origin": "",
    "genesis_date": null,
    "contract_address": "0xa2881f7f441267042f9778ffa0d4f834693426be",
    "url": "https://thehusl.io/",
    "explorers": [
        "https://etherscan.io/token/0xa2881f7f441267042f9778ffa0d4f834693426be",
        "https://ethplorer.io/address/0xa2881f7f441267042f9778ffa0d4f834693426be"
    ],
    "twitter": "The_HUSL",
    "telegram": "TheHUSL"
}