{
    "id": "revamped-music",
    "symbol": "mp3",
    "name": "Revamped Music",
    "platforms": {
        "tron": "TXZHUe5pSkAwrUZ3hRyYhd2m6Jp1giEZSD"
    },
    "hashing_algorithm": null,
    "categories": [],
    "description": {
        "en": "Revamped Music is a next generation music reviewing platform and ecosystem powered by the MP3 token that rewards both the reviewer for their valuable review and also rewards the commenter for commenting on that review."
    },
    "country_origin": "GB",
    "genesis_date": null,
    "contract_address": "TXZHUe5pSkAwrUZ3hRyYhd2m6Jp1giEZSD",
    "url": "https://www.revampedmusic.site/",
    "explorers": [
        "https://tronscan.org/#/token20/TXZHUe5pSkAwrUZ3hRyYhd2m6Jp1giEZSD"
    ],
    "twitter": "RevampedM",
    "facebook": "RevampedM",
    "telegram": "RevampedMusic_Community",
    "reddit": "RevampedMusic/"
}