{
    "id": "saturna",
    "symbol": "sat",
    "name": "Saturna",
    "platforms": {
        "binance-smart-chain": "0x1e446cbea52badeb614fbe4ab7610f737995fb44"
    },
    "hashing_algorithm": null,
    "categories": [],
    "description": {
        "en": "Saturna is here to provide you an opportunity to put away the past and focus on getting to the next moon. If those before have come and gone, then trust that history repeats itself and see where the future is with this next generation of tokens. So break away from the worthless utility clones, stop worrying about APR\u2019s and Impermanent Loss, and stick with a tried-and-true smart contract code that has led prospectors to millions in realized and billions in unrealized funds, and trust one of the fastest growing movements on Binance Smart Chain."
    },
    "country_origin": "",
    "genesis_date": null,
    "contract_address": "0x1e446cbea52badeb614fbe4ab7610f737995fb44",
    "url": "https://saturna.co/",
    "explorers": [
        "https://bscscan.com/token/0x1e446CbEa52BAdeB614FBe4Ab7610F737995fB44"
    ],
    "twitter": "SaturnaToken",
    "telegram": "saturna_TG",
    "reddit": "SaturnaToken/"
}