{
    "id": "poolcoin",
    "symbol": "pool",
    "name": "POOLCOIN",
    "platforms": {},
    "hashing_algorithm": null,
    "categories": [
        "Cryptocurrency"
    ],
    "description": {
        "en": "\"POOLCOIN is a new Alt Cryptocurrency based on SCRYPT (Proof of Work (POW) + Proof of Stake (POS)).\r\nPOOLCOIN was created by Experienced Company (over 10++ years experiences) in Cryptocurrency and Assets Investvent.\r\nOur company now was launch the POOLCOIN and give users FREE POOLCOIN when investing with us Using Arbitrage Trading Platform. \""
    },
    "country_origin": "MY",
    "genesis_date": null,
    "url": "https://poolcoin.world",
    "explorers": [
        "http://poolexplorer.live:3001/"
    ],
    "twitter": "main_poolcoin",
    "telegram": "official_poolcoin",
    "github_org": "devPOOLCOIN"
}