{
    "id": "bitalgo",
    "symbol": "alg",
    "name": "Bitalgo",
    "platforms": {},
    "hashing_algorithm": "Quark",
    "categories": [
        "Cryptocurrency"
    ],
    "description": {
        "en": "Bitalgo as one of the fast-growing cryptocurrencies currently prioritizes aspects of technology, ecosystems, and communities in its development. The technological aspect is very important for the existence of a cryptocurrency because it is a technological product. What distinguishes a digital product whether it is a cryptocurrency or not is its technology."
    },
    "country_origin": "ID",
    "genesis_date": null,
    "url": "https://bitalgocoin.org/",
    "explorers": [
        "https://bitalgochains.info/#/"
    ],
    "twitter": "bitalgo",
    "telegram": "bitalgoteam",
    "github_org": "BitalgoCOIN"
}