{
    "id": "bitcoin-rhodium",
    "symbol": "xrc",
    "name": "xRhodium",
    "platforms": {},
    "hashing_algorithm": "X13",
    "categories": [],
    "description": {
        "en": "xRhodium is a community-based digital asset with limited supply and strong use case. The coin meets all the requirements of users for a long-term investment in cryptocurrency and unites the best of the worlds of crypto and traditional investment. xRhodium gathers a strong community of supporters around the currency in order to raise its awareness in the crypto market. The team also offers Strong Hands partnership programme where holders can earn from 0,5% to 30% of reward on XRC holdings every year.\r\n\r\nxRhodium uses its blockchain with a total supply of 2.1 million XRC. It is programmed in C# language."
    },
    "country_origin": "",
    "genesis_date": null,
    "url": "https://www.xrhodium.org/",
    "explorers": [
        "https://explorer.xrhodium.org/",
        "https://xrc.tokenview.com/"
    ],
    "twitter": "xrhodium_xrc",
    "telegram": "xrhodium_xrc",
    "reddit": "https://www.reddit.com"
}