{
    "id": "hydradx",
    "symbol": "xhdx",
    "name": "HydraDX",
    "platforms": {
        "ethereum": "0x6fcb6408499a7c0f242e32d77eb51ffa1dd28a7e"
    },
    "hashing_algorithm": null,
    "categories": [
        "Polygon Ecosystem"
    ],
    "description": {
        "en": ""
    },
    "country_origin": "",
    "genesis_date": null,
    "contract_address": "0x6fcb6408499a7c0f242e32d77eb51ffa1dd28a7e",
    "url": "https://hydradx.io/",
    "explorers": [
        "https://etherscan.io/token/0x6FCb6408499a7c0f242E32D77EB51fFa1dD28a7E",
        "https://ethplorer.io/address/0x6fcb6408499a7c0f242e32d77eb51ffa1dd28a7e"
    ],
    "twitter": "hydra_dx",
    "telegram": "hydradx",
    "github_org": "galacticcouncil?tab=repositories"
}